retmap/__init__.py
retmap/constants.py
retmap/density.py
retmap/input_reader.py
retmap/interpreter.py
retmap/main.py
retmap/physics.py
retmap/saturation_pressure.py
retmap/library/density/Ar.dat
retmap/library/property/Ar.prop
retmap/library/property/C3H8.prop
retmap/library/property/CH3OH.prop
retmap/library/property/CH4.prop
retmap/library/property/CO2.prop
retmap/library/property/H2.prop
retmap/library/property/H2O.prop
retmap/library/property/N2.prop
retmap/library/property/NH3.prop
retmap/library/saturation-pressure/Ar.dat
retmap/library/saturation-pressure/CH4.dat
retmap/library/saturation-pressure/CO2.dat
retmap/library/saturation-pressure/CO2_critical_density.dat
retmap/library/saturation-pressure/H2_critical_density.dat
retmap/library/saturation-pressure/N2.dat
retmap/library/saturation-pressure/N2_critical_density.dat
retmap/library/saturation-pressure/NH3_critical_density.dat
retmap/library/saturation-pressure/methanol_critical_density.dat
retmap/library/saturation-pressure/propane_critical_density.dat
retmap-1.0a1.dist-info/LICENSE.txt
retmap-1.0a1.dist-info/METADATA
retmap-1.0a1.dist-info/WHEEL
retmap-1.0a1.dist-info/entry_points.txt
retmap-1.0a1.dist-info/top_level.txt
retmap-1.0a1.dist-info/RECORD
