Metadata-Version: 2.1
Name: retmap
Version: 1.0a1
Summary: A Python tool for computing and predicting characteristic curves and isotherms from experimental and simulated data.
Author-email: Flavian Stavarache <f.stavarache@student.tue.nl>, Azahara Luna-Triguero <a.luna.triguero@tue.nl>, Sofía Calero <s.calero@tue.nl>, José Manuel Vicent-Luna <j.vicent.luna@tue.nl>
License: MIT License
Project-URL: Homepage, https://stflavian.github.io/RETMAP/
Project-URL: Documentation, https://stflavian.github.io/RETMAP/manual/configuration/
Project-URL: Repository, https://github.com/stflavian/RETMAP
Project-URL: Issues, https://github.com/stflavian/RETMAP/issues
Keywords: adsorption,adsorption potential theory
Classifier: Environment :: Console
Classifier: Development Status :: 3 - Alpha
Classifier: Intended Audience :: Science/Research
Classifier: License :: OSI Approved :: MIT License
Classifier: Operating System :: OS Independent
Classifier: Programming Language :: Python :: 3
Classifier: Topic :: Scientific/Engineering :: Physics
Requires-Python: >=3.7
License-File: LICENSE.txt
Requires-Dist: scipy
Requires-Dist: numpy
Requires-Dist: matplotlib
